argueview/ArgueView.py
argueview/__init__.py
argueview/typings.py
argueview/helper/__init__.py
argueview/helper/feature_importance.py
argueview/visualizers/FeatureListVisualizer.py
argueview/visualizers/ToulminVisualizer.py
argueview/visualizers/__init__.py
argueview/visualizers/initjs.py
argueview-0.2.1.dist-info/LICENSE
argueview-0.2.1.dist-info/METADATA
argueview-0.2.1.dist-info/WHEEL
argueview-0.2.1.dist-info/top_level.txt
argueview-0.2.1.dist-info/RECORD
