Metadata-Version: 2.1
Name: argueview
Version: 0.2.1
Summary: ArgueView is a tool for generating text-based presentations for machine-learning predictions and feature-importance based explanation tools. The tool makes use of Toulmin's model of argumentation for structuring the text-based explanations.
Home-page: https://github.com/SophiaHadash/ArgueView
Author: Sophia Hadash
Author-email: s.hadash@tue.nl
License: UNKNOWN
Keywords: explanations,text,toulmin,argumentation
Platform: UNKNOWN
Classifier: Programming Language :: Python :: 3
Classifier: License :: OSI Approved :: GNU General Public License v3 (GPLv3)
Classifier: Operating System :: OS Independent
Classifier: Intended Audience :: Science/Research
Classifier: Topic :: Scientific/Engineering :: Artificial Intelligence
Classifier: Development Status :: 3 - Alpha
Requires-Python: >=3.5
Requires-Dist: anchor-exp (==0.0.2.0)
Requires-Dist: backcall (==0.2.0)
Requires-Dist: certifi (==2020.12.5)
Requires-Dist: chardet (==3.0.4)
Requires-Dist: cycler (==0.10.0)
Requires-Dist: cymem (==2.0.5)
Requires-Dist: decorator (==4.4.2)
Requires-Dist: imageio (==2.9.0)
Requires-Dist: ipython-genutils (==0.2.0)
Requires-Dist: ipython (==7.19.0)
Requires-Dist: jsonpickle (==1.4.1)
Requires-Dist: murmurhash (==1.0.5)
Requires-Dist: numpy (==1.19.4)
Requires-Dist: pickleshare (==0.7.5)
Requires-Dist: plac (==1.1.3)
Requires-Dist: preshed (==3.0.5)
Requires-Dist: ptyprocess (==0.6.0)
Requires-Dist: scipy (==1.5.4)
Requires-Dist: srsly (==1.0.5)
Requires-Dist: thinc (==7.4.3)
Requires-Dist: wasabi (==0.8.0)
Requires-Dist: wcwidth (==0.2.5)
Requires-Dist: prompt-toolkit (==3.0.8) ; python_full_version >= "3.6.1"
Requires-Dist: pyparsing (==2.4.7) ; python_version >= "2.6" and python_version not in "3.0, 3.1, 3.2, 3.3"
Requires-Dist: catalogue (==1.0.0) ; python_version >= "2.7" and python_version not in "3.0, 3.1, 3.2, 3.3"
Requires-Dist: idna (==2.10) ; python_version >= "2.7" and python_version not in "3.0, 3.1, 3.2, 3.3"
Requires-Dist: parso (==0.7.1) ; python_version >= "2.7" and python_version not in "3.0, 3.1, 3.2, 3.3"
Requires-Dist: python-dateutil (==2.8.1) ; python_version >= "2.7" and python_version not in "3.0, 3.1, 3.2, 3.3"
Requires-Dist: six (==1.15.0) ; python_version >= "2.7" and python_version not in "3.0, 3.1, 3.2, 3.3"
Requires-Dist: tqdm (==4.54.1) ; python_version >= "2.7" and python_version not in "3.0, 3.1, 3.2, 3.3"
Requires-Dist: jedi (==0.17.2) ; python_version >= "2.7" and python_version not in "3.0, 3.1, 3.2, 3.3, 3.4"
Requires-Dist: requests (==2.25.0) ; python_version >= "2.7" and python_version not in "3.0, 3.1, 3.2, 3.3, 3.4"
Requires-Dist: spacy (==2.3.4) ; python_version >= "2.7" and python_version not in "3.0, 3.1, 3.2, 3.3, 3.4"
Requires-Dist: urllib3 (==1.26.2) ; python_version >= "2.7" and python_version not in "3.0, 3.1, 3.2, 3.3, 3.4" and python_version < "4"
Requires-Dist: lime (==0.2.0.1) ; python_version >= "3.5"
Requires-Dist: pygments (==2.7.3) ; python_version >= "3.5"
Requires-Dist: pywavelets (==1.1.1) ; python_version >= "3.5"
Requires-Dist: threadpoolctl (==2.1.0) ; python_version >= "3.5"
Requires-Dist: blis (==0.7.4) ; python_version >= "3.6"
Requires-Dist: importlib-metadata (==3.1.1) ; python_version >= "3.6"
Requires-Dist: joblib (==0.17.0) ; python_version >= "3.6"
Requires-Dist: kiwisolver (==1.3.1) ; python_version >= "3.6"
Requires-Dist: matplotlib (==3.3.3) ; python_version >= "3.6"
Requires-Dist: networkx (==2.5) ; python_version >= "3.6"
Requires-Dist: pillow (==8.0.1) ; python_version >= "3.6"
Requires-Dist: scikit-image (==0.17.2) ; python_version >= "3.6"
Requires-Dist: scikit-learn (==0.23.2) ; python_version >= "3.6"
Requires-Dist: zipp (==3.4.0) ; python_version >= "3.6"
Requires-Dist: tifffile (==2020.12.4) ; python_version >= "3.7"
Requires-Dist: traitlets (==5.0.5) ; python_version >= "3.7"
Requires-Dist: pexpect (==4.8.0) ; sys_platform != "win32"
